L2dvExApi/__init__.py
L2dvExApi/msg_list.py
l2dexapi-1.2.dist-info/METADATA
l2dexapi-1.2.dist-info/WHEEL
l2dexapi-1.2.dist-info/top_level.txt
l2dexapi-1.2.dist-info/RECORD
